{
    "keep": {
        "days": true,
        "amount": 14
    },
    "auditLog": "C:\\Next Level Course\\UniversityManagement\\UniversityManagementServer\\logs\\winston\\errors\\.b6dd60364467b5d08bc86975939dbb4657c6f140-audit.json",
    "files": [
        {
            "date": 1689864279439,
            "name": "C:\\Next Level Course\\UniversityManagement\\UniversityManagementServer\\logs\\winston\\errors\\um-2023-07-20-20-error.log",
            "hash": "298c2f5678e924f3f88528038cca9372681c03c8cb1aa76fc1ac19438f76d308"
        },
        {
            "date": 1689866485194,
            "name": "C:\\Next Level Course\\UniversityManagement\\UniversityManagementServer\\logs\\winston\\errors\\um-2023-07-20-21-error.log",
            "hash": "38225798a7db5a70bd2727cfa3abb41be4fe630030eaaa19896227be066675a6"
        },
        {
            "date": 1689868946616,
            "name": "C:\\Next Level Course\\UniversityManagement\\UniversityManagementServer\\logs\\winston\\errors\\um-2023-07-20-22-error.log",
            "hash": "c8571b1dbfc354a962af8e6ecc72d6ff40ef42b897a8e6ed715ec005d4ea73cd"
        },
        {
            "date": 1690286356160,
            "name": "C:\\Next Level Course\\UniversityManagement\\UniversityManagementServer\\logs\\winston\\errors\\um-2023-07-25-17-error.log",
            "hash": "2974fbf94023b2fa8afc9a3bdd5f8a08b75ab8e525d9cd95de367135468e3824"
        },
        {
            "date": 1690288629779,
            "name": "C:\\Next Level Course\\UniversityManagement\\UniversityManagementServer\\logs\\winston\\errors\\um-2023-07-25-18-error.log",
            "hash": "094f8dfd9781b18c7190bc2ee0f09763214a9924171d6245ec1af971361ba724"
        },
        {
            "date": 1690290164647,
            "name": "C:\\Next Level Course\\UniversityManagement\\UniversityManagementServer\\logs\\winston\\errors\\um-2023-07-25-19-error.log",
            "hash": "db345ccb6e5ba232ae2296fd615a0a585d74851b3b5a4c298c894f9522e20288"
        },
        {
            "date": 1690297762844,
            "name": "C:\\Next Level Course\\UniversityManagement\\UniversityManagementServer\\logs\\winston\\errors\\um-2023-07-25-21-error.log",
            "hash": "f4bb5cd3a208c23f62da0eb46b78ad16f529d6d9c65fd2f1b37133541f29a571"
        }
    ],
    "hashType": "sha256"
}